font_colors/__init__.py
font_colors/back.py
font_colors/color.py
font_colors/style.py
font_colors-1.0.2.dist-info/LICENCE
font_colors-1.0.2.dist-info/METADATA
font_colors-1.0.2.dist-info/WHEEL
font_colors-1.0.2.dist-info/top_level.txt
font_colors-1.0.2.dist-info/RECORD
