Metadata-Version: 2.1
Name: font_colors
Version: 1.0.2
Summary: none
Author: Arsam
Author-email: ashouriarsam@gmail.com
License-File: LICENCE
Requires-Dist: colorama
